README.rst
setup.py
libgiza/__init__.py
libgiza/app.py
libgiza/config.py
libgiza/error.py
libgiza/git.py
libgiza/graph.py
libgiza/inheritance.py
libgiza/libgit.py
libgiza/pool.py
libgiza/task.py
libgiza/typed_dict.py
libgiza.egg-info/PKG-INFO
libgiza.egg-info/SOURCES.txt
libgiza.egg-info/dependency_links.txt
libgiza.egg-info/requires.txt
libgiza.egg-info/top_level.txt
libgiza/test/__init__.py
libgiza/test/test_app.py
libgiza/test/test_config.py
libgiza/test/test_error.py
libgiza/test/test_inheritance.py
libgiza/test/test_task.py
libgiza/test/test_typed_dict.py
libgiza/test/data-inheritance/example-add-one.yaml
libgiza/test/data-inheritance/example-add-three.yaml
libgiza/test/data-inheritance/example-add-two.yaml