Metadata-Version: 1.1
Name: libgiza
Version: 0.2.13
Summary: Build System Toolkit
Home-page: http://github.com/tychoish/libgiza/
Author: tychoish
Author-email: sam@tychoish.com
License: Apache 2.0
Platform: UNKNOWN
Classifier: Environment :: Console
Classifier: Intended Audience :: Developers
Classifier: Topic :: Software Development :: Testing
Classifier: Programming Language :: Python
Classifier: Programming Language :: Python :: 2
Classifier: License :: OSI Approved :: Apache Software License
Classifier: Topic :: Software Development :: Libraries
Classifier: Topic :: Software Development :: Build Tools
